startggapi/__init__.py
startggapi/__version__.py
startggapi/startggapi.py
startggapi/_apis/BaseApi.py
startggapi/_apis/EntrantApi.py
startggapi/_apis/EventApi.py
startggapi/_apis/QueryStrings.py
startggapi/_apis/TournamentApi.py
startggapi/_apis/VideogameApi.py
startggapi/_apis/__init__.py
startggapi-0.1.22.dist-info/LICENSE
startggapi-0.1.22.dist-info/METADATA
startggapi-0.1.22.dist-info/WHEEL
startggapi-0.1.22.dist-info/top_level.txt
startggapi-0.1.22.dist-info/RECORD
