Metadata-Version: 2.1
Name: startggapi
Version: 0.1.22
Summary: StartGGApi is a thin wrapper on top of the StartGG GraphQL APIs
Home-page: https://github.com/Caja-de-Dano/StartGG-API
Author: Lucky Daisy LLC
License: MIT
Classifier: License :: OSI Approved :: MIT License
Classifier: Topic :: Software Development :: Libraries :: Python Modules
License-File: LICENSE
Requires-Dist: requests
Provides-Extra: dev
Requires-Dist: coverage ; extra == 'dev'
Requires-Dist: pre-commit ; extra == 'dev'
Requires-Dist: pytest ; extra == 'dev'
Requires-Dist: pytest-cov ; extra == 'dev'
Requires-Dist: tox ; extra == 'dev'
Requires-Dist: responses ; extra == 'dev'
